LICENSE
MANIFEST.in
README.rst
requirements.txt
setup.py
src/Poio_API.egg-info/PKG-INFO
src/Poio_API.egg-info/SOURCES.txt
src/Poio_API.egg-info/dependency_links.txt
src/Poio_API.egg-info/top_level.txt
src/poio_api.egg-info/SOURCES.txt
src/poioapi/VERSION
src/poioapi/__init__.py
src/poioapi/annotationgraph.py
src/poioapi/annotationtree.py
src/poioapi/corpus.py
src/poioapi/corpusreader.py
src/poioapi/data.py
src/poioapi/io/__init__.py
src/poioapi/io/brat.py
src/poioapi/io/elan.py
src/poioapi/io/graf.py
src/poioapi/io/pickle.py
src/poioapi/io/tcf.py
src/poioapi/io/toolbox.py
src/poioapi/io/typecraft.py
src/poioapi/io/wikipedia_extractor.py